humancursor/__init__.py
humancursor/system_cursor.py
humancursor/web_cursor.py
humancursor/HCScripter/__init__.py
humancursor/HCScripter/gui.py
humancursor/HCScripter/launch.py
humancursor/test/system.py
humancursor/test/web.py
humancursor/utilities/calculate_and_randomize.py
humancursor/utilities/human_curve_generator.py
humancursor/utilities/web_adjuster.py
HumanCursor-1.1.5.dist-info/LICENSE
HumanCursor-1.1.5.dist-info/METADATA
HumanCursor-1.1.5.dist-info/WHEEL
HumanCursor-1.1.5.dist-info/top_level.txt
HumanCursor-1.1.5.dist-info/RECORD
