Metadata-Version: 2.1
Name: HumanCursor
Version: 1.1.5
Summary: Simulate Human Cursor Movement for Automated Scripts
Author-email: Flori Batusha <floribatusha0@gmail.com>
Project-URL: Homepage, https://github.com/riflosnake/HumanCursor
Classifier: Programming Language :: Python :: 3
Classifier: License :: OSI Approved :: MIT License
Classifier: Operating System :: OS Independent
Requires-Python: >=3.7
License-File: LICENSE
Requires-Dist: selenium >=4.9.0
Requires-Dist: pyautogui >=0.9.53
Requires-Dist: numpy >=1.24.3
